odoo/addons/contract_sale/README.rst
odoo/addons/contract_sale/__init__.py
odoo/addons/contract_sale/__manifest__.py
odoo/addons/contract_sale/i18n/ca_ES.po
odoo/addons/contract_sale/i18n/contract_sale.pot
odoo/addons/contract_sale/i18n/de.po
odoo/addons/contract_sale/i18n/es.po
odoo/addons/contract_sale/i18n/es_AR.po
odoo/addons/contract_sale/i18n/es_CL.po
odoo/addons/contract_sale/i18n/fr.po
odoo/addons/contract_sale/i18n/gl.po
odoo/addons/contract_sale/i18n/hi_IN.po
odoo/addons/contract_sale/i18n/hr.po
odoo/addons/contract_sale/i18n/hr_HR.po
odoo/addons/contract_sale/i18n/it.po
odoo/addons/contract_sale/i18n/nl.po
odoo/addons/contract_sale/i18n/nl_NL.po
odoo/addons/contract_sale/i18n/pt.po
odoo/addons/contract_sale/i18n/pt_BR.po
odoo/addons/contract_sale/i18n/ro.po
odoo/addons/contract_sale/i18n/ru.po
odoo/addons/contract_sale/i18n/sv.po
odoo/addons/contract_sale/i18n/tr.po
odoo/addons/contract_sale/i18n/tr_TR.po
odoo/addons/contract_sale/i18n/zh_CN.po
odoo/addons/contract_sale/readme/CONTRIBUTORS.md
odoo/addons/contract_sale/readme/DESCRIPTION.md
odoo/addons/contract_sale/readme/USAGE.md
odoo/addons/contract_sale/security/contract_security.xml
odoo/addons/contract_sale/security/ir.model.access.csv
odoo/addons/contract_sale/static/description/icon.png
odoo/addons/contract_sale/static/description/index.html
odoo/addons/contract_sale/tests/__init__.py
odoo/addons/contract_sale/tests/test_sale_contract.py
odoo/addons/contract_sale/views/contract.xml
odoo/addons/contract_sale/views/res_partner_view.xml
odoo_addon_contract_sale-18.0.1.0.0.4.dist-info/METADATA
odoo_addon_contract_sale-18.0.1.0.0.4.dist-info/WHEEL
odoo_addon_contract_sale-18.0.1.0.0.4.dist-info/top_level.txt
odoo_addon_contract_sale-18.0.1.0.0.4.dist-info/RECORD
